fxa/__init__.py
fxa/__main__.py
fxa/_utils.py
fxa/cache.py
fxa/constants.py
fxa/core.py
fxa/crypto.py
fxa/errors.py
fxa/oauth.py
fxa/profile.py
fxa/plugins/__init__.py
fxa/plugins/requests.py
fxa/tests/__init__.py
fxa/tests/bad-key.json
fxa/tests/jwks.json
fxa/tests/mock_utilities.py
fxa/tests/private-key.json
fxa/tests/test_cache.py
fxa/tests/test_core.py
fxa/tests/test_crypto.py
fxa/tests/test_oauth.py
fxa/tests/test_profile.py
fxa/tests/test_requests_auth_plugin.py
fxa/tests/test_tools.py
fxa/tests/utils.py
fxa/tools/__init__.py
fxa/tools/bearer.py
fxa/tools/browserid.py
fxa/tools/create_user.py
fxa/tools/unblock.py
pyfxa_mte-0.7.9.dist-info/METADATA
pyfxa_mte-0.7.9.dist-info/WHEEL
pyfxa_mte-0.7.9.dist-info/entry_points.txt
pyfxa_mte-0.7.9.dist-info/licenses/LICENSE.txt
pyfxa_mte-0.7.9.dist-info/RECORD
