Metadata-Version: 2.3
Name: pyfxa-mte
Version: 0.7.9
Summary: Firefox Accounts client library for Python
Project-URL: Homepage, https://github.com/clarmso/PyFxA
Author-email: Mozilla Services <services-dev@mozilla.org>
License-Expression: MPL-2.0
License-File: LICENSE.txt
Keywords: accounts,authentication,firefox
Classifier: Intended Audience :: Developers
Classifier: License :: OSI Approved :: Mozilla Public License 2.0 (MPL 2.0)
Classifier: Programming Language :: Python
Classifier: Programming Language :: Python :: 3 :: Only
Classifier: Programming Language :: Python :: 3.8
Classifier: Programming Language :: Python :: 3.9
Classifier: Programming Language :: Python :: 3.10
Classifier: Programming Language :: Python :: 3.11
Classifier: Programming Language :: Python :: 3.12
Requires-Python: >=3.8
Requires-Dist: cryptography
Requires-Dist: hawkauthlib
Requires-Dist: pybrowserid
Requires-Dist: pyjwt
Requires-Dist: requests>=2.4.2
